turbotask/__init__.py
turbotask/helper.py
turbotask/main.py
turbotask/workers/__init__.py
turbotask/workers/classes.py
turbotask/workers/groupFiles.py
turbotask-0.2.31.dist-info/METADATA
turbotask-0.2.31.dist-info/WHEEL
turbotask-0.2.31.dist-info/entry_points.txt
turbotask-0.2.31.dist-info/top_level.txt
turbotask-0.2.31.dist-info/RECORD
