Metadata-Version: 2.1
Name: turbotask
Version: 0.2.31
Summary: A command-line tool that Makes Handling files quick and easy.
Home-page: https://github.com/Fector101/TurboTask/
Author: Fabian
Author-email: fabianjoseph063@gmail.com
Classifier: Programming Language :: Python :: 3
Classifier: Operating System :: OS Independent
Requires-Python: >=3.6
Requires-Dist: colorama
